{"kylin.cube.aggrgroup.max-combination": ["org.apache.kylin.tool.CubeMetaExtractorTest#testExtractorByPrj", "org.apache.kylin.tool.HybridCubeCLITest#test3Delete", "org.apache.kylin.tool.HybridCubeCLITest#test2Update", "org.apache.kylin.tool.HybridCubeCLITest#test1Create", "org.apache.kylin.tool.metrics.systemcube.SCCreatorTest#testExecute", "org.apache.kylin.tool.HybridCubeCLITest#testSegmentOverlap", "org.apache.kylin.tool.HybridCubeCLITest#testSegmentNotOverlap"], "kylin.storage.hbase.table-name-prefix": ["org.apache.kylin.tool.HybridCubeCLITest#testSegmentNotOverlap", "org.apache.kylin.tool.HybridCubeCLITest#testSegmentOverlap"], "kylin.cube.rowkey.max-size": ["org.apache.kylin.tool.HybridCubeCLITest#testSegmentOverlap", "org.apache.kylin.tool.HybridCubeCLITest#testSegmentNotOverlap", "org.apache.kylin.tool.HybridCubeCLITest#test1Create", "org.apache.kylin.tool.HybridCubeCLITest#test3Delete", "org.apache.kylin.tool.metrics.systemcube.SCCreatorTest#testExecute", "org.apache.kylin.tool.HybridCubeCLITest#test2Update", "org.apache.kylin.tool.CubeMetaExtractorTest#testExtractorByPrj"], "kylin.cube.aggrgroup.is-mandatory-only-valid": ["org.apache.kylin.tool.HybridCubeCLITest#test2Update", "org.apache.kylin.tool.HybridCubeCLITest#testSegmentOverlap", "org.apache.kylin.tool.HybridCubeCLITest#test1Create", "org.apache.kylin.tool.HybridCubeCLITest#test3Delete", "org.apache.kylin.tool.CubeMetaExtractorTest#testExtractorByPrj", "org.apache.kylin.tool.metrics.systemcube.SCCreatorTest#testExecute", "org.apache.kylin.tool.HybridCubeCLITest#testSegmentNotOverlap"], "kylin.resourcestore.reconnect-base-ms": ["org.apache.kylin.tool.CubeMetaExtractorTest#testExtractorByPrj", "org.apache.kylin.tool.HybridCubeCLITest#test1Create", "org.apache.kylin.tool.HybridCubeCLITest#test3Delete", "org.apache.kylin.tool.HybridCubeCLITest#testSegmentNotOverlap", "org.apache.kylin.tool.metrics.systemcube.SCCreatorTest#testExecute", "org.apache.kylin.tool.HybridCubeCLITest#test2Update", "org.apache.kylin.tool.HybridCubeCLITest#testSegmentOverlap"], "kylin.env": ["org.apache.kylin.tool.metrics.systemcube.SCCreatorTest#testExecute"], "kylin.metadata.check-copy-on-write": ["org.apache.kylin.tool.HybridCubeCLITest#test3Delete", "org.apache.kylin.tool.CubeMetaExtractorTest#testExtractorByPrj", "org.apache.kylin.tool.HybridCubeCLITest#testSegmentNotOverlap", "org.apache.kylin.tool.HybridCubeCLITest#testSegmentOverlap", "org.apache.kylin.tool.metrics.systemcube.SCCreatorTest#testExecute", "org.apache.kylin.tool.HybridCubeCLITest#test1Create", "org.apache.kylin.tool.HybridCubeCLITest#test2Update"]}